verbose_print/__init__.py
verbose_print/style_decorators.py
verbose_print/styles.py
verbose_print/vprint.py
verbose_print-0.0.2.dist-info/LICENSE
verbose_print-0.0.2.dist-info/METADATA
verbose_print-0.0.2.dist-info/WHEEL
verbose_print-0.0.2.dist-info/top_level.txt
verbose_print-0.0.2.dist-info/RECORD
